zeroconf_service/__init__.py
zeroconf_service/utils.py
zeroconf_service/workers.py
zeroconf_service-2.2.0.dist-info/WHEEL
zeroconf_service-2.2.0.dist-info/METADATA
zeroconf_service-2.2.0.dist-info/RECORD
