Metadata-Version: 2.1
Name: zeroconf-service
Version: 2.2.0
Summary: 
License: MIT
Author: Tim Wedde
Author-email: timwedde@icloud.com
Requires-Python: >=3.7,<4.0
Classifier: License :: OSI Approved :: MIT License
Classifier: Programming Language :: Python :: 3
Classifier: Programming Language :: Python :: 3.7
Classifier: Programming Language :: Python :: 3.8
Classifier: Programming Language :: Python :: 3.9
Requires-Dist: compress-pickle (>=1.2.0,<2.0.0)
Requires-Dist: logzero (>=1.6.3,<2.0.0)
Requires-Dist: websockets (>=8.1,<9.0)
Requires-Dist: zeroconf (>=0.28.8,<0.29.0)
